huaweicloudsdkversatile/__init__.py
huaweicloudsdkversatile/v1/__init__.py
huaweicloudsdkversatile/v1/versatile_async_client.py
huaweicloudsdkversatile/v1/versatile_client.py
huaweicloudsdkversatile/v1/model/__init__.py
huaweicloudsdkversatile/v1/model/agent_run_req.py
huaweicloudsdkversatile/v1/model/conversation.py
huaweicloudsdkversatile/v1/model/feedback_reason.py
huaweicloudsdkversatile/v1/model/knowledge_base_retrieval_req.py
huaweicloudsdkversatile/v1/model/message.py
huaweicloudsdkversatile/v1/model/node_message.py
huaweicloudsdkversatile/v1/model/node_run_info.py
huaweicloudsdkversatile/v1/model/node_run_info_inner_error.py
huaweicloudsdkversatile/v1/model/node_run_info_inner_error_error_body.py
huaweicloudsdkversatile/v1/model/plugin_config.py
huaweicloudsdkversatile/v1/model/retrieval_result_info.py
huaweicloudsdkversatile/v1/model/run_agent_request.py
huaweicloudsdkversatile/v1/model/run_agent_response.py
huaweicloudsdkversatile/v1/model/run_workflow_request.py
huaweicloudsdkversatile/v1/model/run_workflow_response.py
huaweicloudsdkversatile/v1/model/search_knowledge_base_request.py
huaweicloudsdkversatile/v1/model/search_knowledge_base_response.py
huaweicloudsdkversatile/v1/model/status.py
huaweicloudsdkversatile/v1/model/upload_agent_file_request.py
huaweicloudsdkversatile/v1/model/upload_agent_file_request_body.py
huaweicloudsdkversatile/v1/model/upload_agent_file_response.py
huaweicloudsdkversatile/v1/model/user_profile.py
huaweicloudsdkversatile/v1/model/workflow_run_req.py
huaweicloudsdkversatile/v1/model/workflow_run_stream_rsp.py
huaweicloudsdkversatile/v1/region/__init__.py
huaweicloudsdkversatile/v1/region/versatile_region.py
huaweicloudsdkversatile-3.1.184.dist-info/METADATA
huaweicloudsdkversatile-3.1.184.dist-info/WHEEL
huaweicloudsdkversatile-3.1.184.dist-info/licenses/LICENSE
huaweicloudsdkversatile-3.1.184.dist-info/RECORD
